{"itemid": "001-101499", "applicability": "", "application": "NULL", "appno": "52502/07", "article": "8;8-1;8-2", "conclusion": "Non-violation de l'art. 8;Partiellement irrecevable", "decisiondate": "", "docname": "AFFAIRE AUNE c. NORV\u00c8GE", "doctype": "HFJUD", "doctypebranch": "CHAMBER", "documentcollectionid": "CASELAW;JUDGMENTS;CHAMBER;FRA;FRE", "documentcollectionid2": "CASELAW;JUDGMENTS;CHAMBER;FRA;FRE", "ecli": "ECLI:CE:ECHR:2010:1028JUD005250207", "externalsources": "", "extractedappno": "", "importance": "2", "introductiondate": "", "isplaceholder": "True", "issue": "", "judges": "", "judgementdate": "28/10/2010 00:00:00", "kpdate": "10/28/2010 12:00:00 AM", "kpdateAsText": "28/10/2010 00:00:00", "kpthesaurus": "451;425;268;376;354", "languageisocode": "FRE", "meetingnumber": "", "nonviolation": "8", "originatingbody": "4", "publishedby": "", "Rank": "0", "referencedate": "", "reportdate": "", "representedby": "THIIS V. K.", "resolutiondate": "", "resolutionnumber": "", "respondent": "NOR", "respondentOrderEng": "34", "rulesofcourt": "", "scl": "Tchepelev c. Russie, n\u00b0 58077/00, 26 juillet 2007;Englert c. Allemagne, 25 ao\u00fbt 1987, s\u00e9rie A n\u00b0 123;Eskelinen et autres c. Finlande, n\u00b0 43803/98, 8 ao\u00fbt 2006;Ex roi de Gr\u00e8ce et autres c. Gr\u00e8ce [GC], n\u00b0 25701/94, CEDH 2000-XII;Forrer-Niedenthal c. Allemagne, n\u00b0 47316/99, 20 f\u00e9vrier 2003;Gnahor\u00e9 c. France, n\u00b0 40031/98, CEDH 2000 IX;G\u00f6rg\u00fcl\u00fc c. Allemagne, n\u00b0 74969/01, 26 f\u00e9vrier 2004;Jahn et autres c. Allemagne [GC], nos 46720/99, 72203/01 et 72552/01, CEDH 2005 VI;Johansen c. Norv\u00e8ge (d\u00e9c.) 12750/02, 10 octobre 2002;Johansen c. Norv\u00e8ge, 7 ao\u00fbt 1996, Recueil des arr\u00eats et d\u00e9cisions 1996 III;Lutz c. Allemagne, 25 ao\u00fbt 1987, s\u00e9rie A n\u00b0 123;Minelli c. Suisse, 25 mars 1983, s\u00e9rie A n\u00b0 62;N\u00f6lkenbockhoff c. Allemagne, 25 ao\u00fbt 1987, s\u00e9rie A n\u00b0 123;Sanchez Cardenas c. Norv\u00e8ge, n\u00b0 12148/03, 4 octobre 2007;Sanchez Cardenas c. Norv\u00e8ge, n\u00b0 12148/03, 4 octobre 2007;Sara Lind Eggertsd\u00f3ttir c. Islande, n\u00b0 31930/04, CEDH 2007-VIII;S\u00f6derb\u00e4ck c. Su\u00e8de, 28 octobre 1998, Recueil 1998-VII;Wittek c. Allemagne, n\u00b0 37290/97, CEDH 2002-X", "separateopinion": "FALSE", "sharepointid": "441262", "typedescription": "15", "violation": ""}