{"itemid": "001-101187", "applicability": "", "application": "MS WORD", "appno": "17444/04", "article": "5;5-3;6;6-1;6-1+6-3-b;6-3-b;6-3-d", "conclusion": "Remainder inadmissible;No violation of Art. 5-3;Violation of Art. 6-3-d;Violation of Art. 6-1+6-3-b;Non-pecuniary damage - award", "decisiondate": "", "docname": "CASE OF KORNEV AND KARPENKO v. UKRAINE", "doctype": "HEJUD", "doctypebranch": "CHAMBER", "documentcollectionid": "CASELAW;JUDGMENTS;CHAMBER;ENG", "documentcollectionid2": "CASELAW;JUDGMENTS;CHAMBER;ENG", "ecli": "ECLI:CE:ECHR:2010:1021JUD001744404", "externalsources": "", "extractedappno": "17444/04;56529/00;25642/94;2192/03;33354/96;38789/04;61406/00;9300/81;27245/95;63378/00;29835/96;33268/03;7460/03", "importance": "3", "introductiondate": "", "isplaceholder": "False", "issue": "", "judges": "Ganna Yudkivska;Karel Jungwiert;Mark Villiger;Mirjana Lazarova Trajkovska;Peer Lorenzen;Renate Jaeger;Zdravka Kalaydjieva", "judgementdate": "21/10/2010 00:00:00", "kpdate": "10/21/2010 12:00:00 AM", "kpdateAsText": "21/10/2010 00:00:00", "kpthesaurus": "448;30;445;76;136;11;12;122", "languageisocode": "ENG", "meetingnumber": "", "nonviolation": "5;5-3", "originatingbody": "23", "publishedby": "", "Rank": "0", "referencedate": "", "reportdate": "", "representedby": "BUSHCHENKO A. P.", "resolutiondate": "", "resolutionnumber": "", "respondent": "UKR", "respondentOrderEng": "48", "rulesofcourt": "", "scl": "Aquilina v. Malta [GC], no. 25642/94, ECHR 1999-III;Ashughyan v. Armenia, no. 33268/03, 17 July 2008;Benham v. the United Kingdom, judgment of 10 June 1996, Reports of Judgments and Decisions 1996-III, pp. 752-53;Brogan and Others v. the United Kingdom, 29 November 1988, Series A no. 145-B;C.G.P. v. the Netherlands, (dec.), no. 29835/96, 15 January 1997;Can v. Austria, no. 9300/81, Commission\u2019s report of 12 July 1984, Series A no. 96;Connolly v. the United Kingdom (dec.), no. 27245/95, 26 June 1996;De Jong, Baljet and Van den Brink v. the Netherlands, 22 May 1984, Series A no. 77;Doorson v. the Netherlands, judgment of 26 March 1996, Reports 1996-II, p. 472;Enhorn v. Sweden, no. 56529/00, ECHR 2005-...;Eriksen v. Norway, judgment of 27 May 1997, Reports 1997-III, pp. 861-62;F.C.B. v. Italy, judgment of 28 August 1991, Series A no. 208-B, p. 20;Foucher v. France, judgment of 18 March 1997, Reports 1997-II;Gurepka v. Ukraine (no. 2), no. 38789/04, 8 April 2010;Gurepka v. Ukraine, no. 61406/00, 6 September 2005;Harkmann v. Estonia (dec.), no. 2192/03, 1 March 2005;Luc\u00e0 v. Italy, no. 33354/96, 27 February 2001;L\u00fcdi v. Switzerland, 15 June 1992, Series A no. 238;Mayzit v. Russia, no. 63378/00, 20 January 2005;Nadtochiy v. Ukraine, no. 7460/03, 15 May 2008;Poitrimol v. France, 23 November 1993, Series A no. 277-A;Sa\u00efdi v. France, 20 September 1993, Series A no. 261-C;Schiesser v. Switzerland, 4 December 1979, Series A no. 34;Solakov v. \u201cthe former Yugoslav Republic of Macedonia\u201d, no. 47023/99, ECHR 2001-X;Unterpertinger v. Austria, 24 November 1986, Series A no. 110", "separateopinion": "FALSE", "sharepointid": "358219", "typedescription": "15", "violation": "6;6-3-d;6-1+6-3-b;6-1;6-3-b"}