{"itemid": "001-124819", "applicability": "", "application": "ACROBAT", "appno": "13797/02", "article": "5;5-3;6;6-1;6-2;29;29-3;41", "conclusion": "Violation of Art. 5-3;Violation of Art. 6-1 (composition of state security court);Violation of Art. 6-1 (length of proceedings);Not necessary to examine under Art. 6-2 and 6-3-d;Pecuniary and non-pecuniary damage - financial award;Costs and expenses partial award - domestic proceedings;Costs and expenses partial award - Convention proceedings", "decisiondate": "", "docname": "CASE OF \u015eUYUR v. TURKEY - [Turkish Translation] summary by the Turkish Ministry of Foreign Affairs", "doctype": "HJUDTUR", "doctypebranch": "CHAMBER", "documentcollectionid": "CASELAW;JUDGMENTS;CHAMBER;TUR", "documentcollectionid2": "CASELAW;JUDGMENTS;CHAMBER;TUR", "ecli": "ECLI:CE:ECHR:2006:0523JUD001379702", "externalsources": "", "extractedappno": "13797/02;59659/00;25444/94;46221/99", "importance": "4", "introductiondate": "", "isplaceholder": "False", "issue": "", "judges": "", "judgementdate": "23/05/2006 00:00:00", "kpdate": "5/23/2006 12:00:00 AM", "kpdateAsText": "23/05/2006 00:00:00", "kpthesaurus": "445;76;180;181;406;448;227;216", "languageisocode": "TUR", "meetingnumber": "", "nonviolation": "", "originatingbody": "5", "publishedby": "", "Rank": "0", "referencedate": "", "reportdate": "", "representedby": "KURBANOGLU S.", "resolutiondate": "", "resolutionnumber": "", "respondent": "TUR", "respondentOrderEng": "47", "rulesofcourt": "", "scl": "\u00c7iraklar v. Turkey, judgment of 28 October 1998, Reports 1998-VII, \u00a7 45;Demirel v. Turkey, no. 39324/98, \u00a7\u00a7 47-49, \u00a7 59, 28 April 2003;Incal v Turkey, judgment of 9 June 1998, Reports of Judgments and Decisions 1998-IV, \u00a7 74;Letellier v. France, judgment of 26 June 1991, Series A no. 207;Mansur v. Turkey, judgment of 8 June 1995, Series A no. 319-B, \u00a7 55;\u00d6calan v. Turkey, [GC], no. 46221/99, \u00a7 210, CEDH 2005-...;\u00d6zdemir v. Turkey, no. 59659/00, \u00a7\u00a7 35-36, 6 February 2003;\u00d6zel v. Turkey, no. 42739/98, \u00a7\u00a7 20-21, \u00a7\u00a7 33-34, 7 November 2002;P\u00e9lissier and Sassi v. France [GC], no. 25444/94, \u00a7 67, ECHR 1999-II;Tomasi v. France, judgment of 27 August 1992, Series A no. 241-A", "separateopinion": "FALSE", "sharepointid": "377157", "typedescription": "15", "violation": "5;5-3;6;6-1"}