{"itemid": "001-122499", "applicability": "", "application": "MS WORD", "appno": "31679/96", "article": "8;8-1;41", "conclusion": "Violation of Art. 8;Non-pecuniary damage - financial award;Costs and expenses partial award - domestic proceedings;Costs and expenses partial award - Convention proceedings", "decisiondate": "", "docname": "CASE OF IGNACCOLO-ZENIDE v. ROMANIA - [Romanian translation] provided by the SCM Romania and Monitorul Oficial R.A", "doctype": "HJUDRUM", "doctypebranch": "CHAMBER", "documentcollectionid": "CASELAW;JUDGMENTS;CHAMBER;RON;RUM", "documentcollectionid2": "CASELAW;JUDGMENTS;CHAMBER;RON;RUM", "ecli": "ECLI:CE:ECHR:2000:0125JUD003167996", "externalsources": "", "extractedappno": "679/96", "importance": "1", "introductiondate": "", "isplaceholder": "False", "issue": "", "judges": "Elisabeth Palm", "judgementdate": "25/01/2000 00:00:00", "kpdate": "1/25/2000 12:00:00 AM", "kpdateAsText": "25/01/2000 00:00:00", "kpthesaurus": "451;425;310;238;216", "languageisocode": "RUM", "meetingnumber": "", "nonviolation": "", "originatingbody": "4", "publishedby": "Reports of Judgments and Decisions 2000-I", "Rank": "0", "referencedate": "27/01/1999 00:00:00", "reportdate": "", "representedby": "N/A", "resolutiondate": "", "resolutionnumber": "", "respondent": "ROU", "respondentOrderEng": "37", "rulesofcourt": "", "scl": "", "separateopinion": "TRUE", "sharepointid": "438472", "typedescription": "15", "violation": "8"}