{"itemid": "001-101333", "applicability": "", "application": "MS WORD", "appno": "1643/06", "article": "6;6-1;41", "conclusion": "Violation de l'art. 6-1;Pr\u00e9judice moral - constat de violation suffisant", "decisiondate": "", "docname": "AFFAIRE SUDA c. R\u00c9PUBLIQUE TCH\u00c8QUE", "doctype": "HFJUD", "doctypebranch": "CHAMBER", "documentcollectionid": "CASELAW;JUDGMENTS;CHAMBER;FRA;FRE", "documentcollectionid2": "CASELAW;JUDGMENTS;CHAMBER;FRA;FRE", "ecli": "ECLI:CE:ECHR:2010:1028JUD000164306", "externalsources": "", "extractedappno": "1643/06;2921/03;28464/04;5344/05;637/05;55129/00;8588/79;8589/79;31737/96;10881/84;35943/02;44324/98", "importance": "3", "introductiondate": "", "isplaceholder": "False", "issue": "Article 106 \u00a7 1 du code de proc\u00e9dure civile ; Articles 31 et 34 \u00a7 1 de la loi no 216/1994 ; Articles 131 \u00a7 3 c), 220h \u00a7 4 et 220l du code de commerce", "judges": "Isabelle Berro-Lef\u00e8vre;Karel Jungwiert;Mark Villiger;Peer Lorenzen;Rait Maruste;Renate Jaeger;Zdravka Kalaydjieva", "judgementdate": "28/10/2010 00:00:00", "kpdate": "10/28/2010 12:00:00 AM", "kpdateAsText": "28/10/2010 00:00:00", "kpthesaurus": "445;40;7;216", "languageisocode": "FRE", "meetingnumber": "", "nonviolation": "", "originatingbody": "23", "publishedby": "", "Rank": "0", "referencedate": "", "reportdate": "", "representedby": "ZIMA P.", "resolutiondate": "", "resolutionnumber": "", "respondent": "CZE", "respondentOrderEng": "11", "rulesofcourt": "", "scl": "Bramelid et Malmstr\u00f6m c. Su\u00e8de, nos 8588/79 et 8589/79, d\u00e9cision de la Commission du 12 octobre 1989, D\u00e9cisions et rapports (DR) no 29;Deweer c. Belgique, 27 f\u00e9vrier 1980, s\u00e9rie A no 35;Kind c. Allemagne (d\u00e9c.), no 44324/98, 30 mars 2000;Kohlhofer et Minarik c. R\u00e9publique tch\u00e8que, nos 2921/03, 28464/04 et 5344/05, 15 octobre 2009;Lithgow et autres c. Royaume-Uni, 8 juillet 1986, s\u00e9rie A no 102;Osmo Suovaniemi et autres c. Finlande (d\u00e9c.), no 31737/96, 23 f\u00e9vrier 1999;R. c. Suisse, no 10881/84, d\u00e9cision de la Commission du 4 mars 1987, DR no 51;Transado - Transportes Fluviais do Sado, S.A. c. Portugal (d\u00e9c.), no 35943/02, 16 d\u00e9cembre 2003", "separateopinion": "FALSE", "sharepointid": "361903", "typedescription": "15", "violation": "6;6-1"}