{"itemid": "001-100663", "applicability": "", "application": "MS WORD", "appno": "43578/06;19435/07;21338/07;23022/07;23593/07;25297/07;28442/07;28660/07;30287/07;33161/07;40602/07;51107/07;51354/07;52279/07;52280/07;42131/08;43194/08;51692/08;52128/08;58990/08;59582/08;59834/08;60533/08;60790/08;3456/09;3514/09;4193/09;4550/09;5402/09;6194/09;6198/09;7214/09;7229/09;9021/09", "article": "6;6-1", "conclusion": "Violation de l'art. 6-1;Violation de P1-1", "decisiondate": "", "docname": "AFFAIRE MATVEYEV ET AUTRES c. RUSSIE", "doctype": "HFJUD", "doctypebranch": "CHAMBER", "documentcollectionid": "CASELAW;JUDGMENTS;CHAMBER;FRA;FRE", "documentcollectionid2": "CASELAW;JUDGMENTS;CHAMBER;FRA;FRE", "ecli": "ECLI:CE:ECHR:2010:0930JUD004357806", "externalsources": "", "extractedappno": "43578/06;19435/07;21338/07;23022/07;23593/07;25297/07;28442/07;28660/07;30287/07;33161/07;40602/07;51107/07;51354/07;52279/07;52280/07;42131/08;43194/08;51692/08;52128/08;58990/08;59582/08;59834/08;60533/08;60790/08;3456/09;3514/09;4193/09;4550/09;5402/09;6194/09;6198/09;7214/09;7229/09;9021/09;33509/04;59498/00;22000/03;23113/08", "importance": "4", "introductiondate": "", "isplaceholder": "False", "issue": "", "judges": "Anatoly Kovler;Christos Rozakis;Elisabeth Steiner;George Nicolaou;Giorgio Malinverni;Khanlar Hajiyev", "judgementdate": "30/09/2010 00:00:00", "kpdate": "9/30/2010 12:00:00 AM", "kpdateAsText": "30/09/2010 00:00:00", "kpthesaurus": "445", "languageisocode": "FRE", "meetingnumber": "", "nonviolation": "", "originatingbody": "4", "publishedby": "", "Rank": "0", "referencedate": "", "reportdate": "", "representedby": "N/A", "resolutiondate": "", "resolutionnumber": "", "respondent": "RUS", "respondentOrderEng": "38", "rulesofcourt": "", "scl": "", "separateopinion": "FALSE", "sharepointid": "358137", "typedescription": "15", "violation": "6;6-1"}