{"itemid": "001-100026", "applicability": "", "application": "MS WORD", "appno": "13916/06", "article": "", "conclusion": "Violation of P1-1", "decisiondate": "", "docname": "CASE OF YERANOSYAN AND OTHERS v. ARMENIA", "doctype": "HEJUD", "doctypebranch": "CHAMBER", "documentcollectionid": "CASELAW;JUDGMENTS;CHAMBER;ENG", "documentcollectionid2": "CASELAW;JUDGMENTS;CHAMBER;ENG", "ecli": "ECLI:CE:ECHR:2010:0720JUD001391606", "externalsources": "", "extractedappno": "13916/06;27651/05;25701/94;33202/96;31107/96;21132/05;11253/07", "importance": "4", "introductiondate": "", "isplaceholder": "False", "issue": "", "judges": "Alvina Gyulumyan;Elisabet Fura;Ineta Ziemele;Josep Casadevall;Luis L\u00f3pez Guerra", "judgementdate": "20/07/2010 00:00:00", "kpdate": "7/20/2010 12:00:00 AM", "kpdateAsText": "20/07/2010 00:00:00", "kpthesaurus": "", "languageisocode": "ENG", "meetingnumber": "", "nonviolation": "", "originatingbody": "6", "publishedby": "", "Rank": "0", "referencedate": "", "reportdate": "", "representedby": "MARGARYAN G.", "resolutiondate": "", "resolutionnumber": "", "respondent": "ARM", "respondentOrderEng": "3", "rulesofcourt": "", "scl": "", "separateopinion": "FALSE", "sharepointid": "357877", "typedescription": "15", "violation": ""}