{"itemid": "001-100482", "applicability": "", "application": "NULL", "appno": "33929/03", "article": "3", "conclusion": "Violation de l'art. 3", "decisiondate": "", "docname": "AFFAIRE ALEKSANDR LEONIDOVICH IVANOV c. RUSSIE", "doctype": "HFJUD", "doctypebranch": "CHAMBER", "documentcollectionid": "CASELAW;JUDGMENTS;CHAMBER;FRA;FRE", "documentcollectionid2": "CASELAW;JUDGMENTS;CHAMBER;FRA;FRE", "ecli": "ECLI:CE:ECHR:2010:0923JUD003392903", "externalsources": "", "extractedappno": "", "importance": "4", "introductiondate": "", "isplaceholder": "True", "issue": "", "judges": "", "judgementdate": "23/09/2010 00:00:00", "kpdate": "9/23/2010 12:00:00 AM", "kpdateAsText": "23/09/2010 00:00:00", "kpthesaurus": "350", "languageisocode": "FRE", "meetingnumber": "", "nonviolation": "", "originatingbody": "4", "publishedby": "", "Rank": "0", "referencedate": "", "reportdate": "", "representedby": "IVANOVA T.", "resolutiondate": "", "resolutionnumber": "", "respondent": "RUS", "respondentOrderEng": "38", "rulesofcourt": "", "scl": "", "separateopinion": "FALSE", "sharepointid": "361862", "typedescription": "15", "violation": "3"}